[
	{
		"amount_left" : 0,
		"amount_total" : 0,
		"frequency" : "Daily",
		"id" : 451,
		"is_active" : false,
		"is_validated" : true,
		"item_conditions" : 
		[
			{
				"condition" : "GreaterThan",
				"item_type" : "THREAD",
				"material" : "INORGANIC:ADAMANTINE",
				"reaction_id" : "ADAMANTINE_WAFERS",
				"value" : 0
			},
			{
				"condition" : "GreaterThan",
				"item_type" : "BAR",
				"material" : "COAL",
				"value" : 0
			}
		],
		"job" : "CustomReaction",
		"reaction" : "ADAMANTINE_WAFERS"
	},
	{
		"amount_left" : 0,
		"amount_total" : 0,
		"frequency" : "Daily",
		"id" : 467,
		"is_active" : false,
		"is_validated" : true,
		"item_conditions" : 
		[
			{
				"condition" : "GreaterThan",
				"flags" : 
				[
					"melt_designated",
					"allow_melt_dump"
				],
				"value" : 0
			},
			{
				"condition" : "GreaterThan",
				"item_type" : "BAR",
				"material" : "COAL",
				"value" : 0
			}
		],
		"job" : "MeltMetalObject"
	},
	{
		"amount_left" : 0,
		"amount_total" : 0,
		"frequency" : "Daily",
		"id" : 454,
		"is_active" : false,
		"is_validated" : true,
		"item_conditions" : 
		[
			{
				"bearing" : "SILVER",
				"condition" : "GreaterThan",
				"item_type" : "BOULDER",
				"reaction_id" : "BILLON_MAKING",
				"value" : 0
			},
			{
				"bearing" : "COPPER",
				"condition" : "GreaterThan",
				"item_type" : "BOULDER",
				"reaction_id" : "BILLON_MAKING",
				"value" : 0
			},
			{
				"condition" : "GreaterThan",
				"item_type" : "BAR",
				"material" : "COAL",
				"value" : 0
			}
		],
		"job" : "CustomReaction",
		"reaction" : "BILLON_MAKING"
	},
	{
		"amount_left" : 0,
		"amount_total" : 0,
		"frequency" : "Daily",
		"id" : 452,
		"is_active" : false,
		"is_validated" : true,
		"item_conditions" : 
		[
			{
				"condition" : "GreaterThan",
				"item_type" : "BAR",
				"material" : "INORGANIC:TIN",
				"reaction_id" : "BISMUTH_BRONZE_MAKING",
				"value" : 0
			},
			{
				"condition" : "GreaterThan",
				"item_type" : "BAR",
				"material" : "INORGANIC:COPPER",
				"reaction_id" : "BISMUTH_BRONZE_MAKING",
				"value" : 0
			},
			{
				"condition" : "GreaterThan",
				"item_type" : "BAR",
				"material" : "INORGANIC:BISMUTH",
				"reaction_id" : "BISMUTH_BRONZE_MAKING",
				"value" : 0
			},
			{
				"condition" : "GreaterThan",
				"item_type" : "BAR",
				"material" : "COAL",
				"value" : 0
			}
		],
		"job" : "CustomReaction",
		"reaction" : "BISMUTH_BRONZE_MAKING"
	},
	{
		"amount_left" : 0,
		"amount_total" : 0,
		"frequency" : "Daily",
		"id" : 453,
		"is_active" : false,
		"is_validated" : true,
		"item_conditions" : 
		[
			{
				"condition" : "GreaterThan",
				"item_type" : "BAR",
				"material" : "INORGANIC:COPPER",
				"reaction_id" : "BLACK_BRONZE_MAKING",
				"value" : 0
			},
			{
				"condition" : "GreaterThan",
				"item_type" : "BAR",
				"material" : "INORGANIC:SILVER",
				"reaction_id" : "BLACK_BRONZE_MAKING",
				"value" : 0
			},
			{
				"condition" : "GreaterThan",
				"item_type" : "BAR",
				"material" : "INORGANIC:GOLD",
				"reaction_id" : "BLACK_BRONZE_MAKING",
				"value" : 0
			},
			{
				"condition" : "GreaterThan",
				"item_type" : "BAR",
				"material" : "COAL",
				"value" : 0
			}
		],
		"job" : "CustomReaction",
		"reaction" : "BLACK_BRONZE_MAKING"
	},
	{
		"amount_left" : 0,
		"amount_total" : 0,
		"frequency" : "Daily",
		"id" : 455,
		"is_active" : false,
		"is_validated" : true,
		"item_conditions" : 
		[
			{
				"bearing" : "ZINC",
				"condition" : "GreaterThan",
				"item_type" : "BOULDER",
				"reaction_id" : "BRASS_MAKING",
				"value" : 0
			},
			{
				"bearing" : "COPPER",
				"condition" : "GreaterThan",
				"item_type" : "BOULDER",
				"reaction_id" : "BRASS_MAKING",
				"value" : 0
			},
			{
				"condition" : "GreaterThan",
				"item_type" : "BAR",
				"material" : "COAL",
				"value" : 0
			}
		],
		"job" : "CustomReaction",
		"reaction" : "BRASS_MAKING"
	},
	{
		"amount_left" : 0,
		"amount_total" : 0,
		"frequency" : "Daily",
		"id" : 456,
		"is_active" : false,
		"is_validated" : true,
		"item_conditions" : 
		[
			{
				"condition" : "GreaterThan",
				"item_type" : "BOULDER",
				"material" : "INORGANIC:COAL_BITUMINOUS",
				"reaction_id" : "BITUMINOUS_COAL_TO_COKE",
				"value" : 0
			},
			{
				"condition" : "GreaterThan",
				"item_type" : "BAR",
				"material" : "COAL",
				"value" : 0
			}
		],
		"job" : "CustomReaction",
		"reaction" : "BITUMINOUS_COAL_TO_COKE"
	},
	{
		"amount_left" : 0,
		"amount_total" : 0,
		"frequency" : "Daily",
		"id" : 457,
		"is_active" : false,
		"is_validated" : true,
		"item_conditions" : 
		[
			{
				"condition" : "GreaterThan",
				"item_type" : "BOULDER",
				"material" : "INORGANIC:LIGNITE",
				"reaction_id" : "LIGNITE_TO_COKE",
				"value" : 0
			},
			{
				"condition" : "GreaterThan",
				"item_type" : "BAR",
				"material" : "COAL",
				"value" : 0
			}
		],
		"job" : "CustomReaction",
		"reaction" : "LIGNITE_TO_COKE"
	},
	{
		"amount_left" : 0,
		"amount_total" : 0,
		"frequency" : "Daily",
		"id" : 458,
		"is_active" : false,
		"is_validated" : true,
		"item_conditions" : 
		[
			{
				"bearing" : "SILVER",
				"condition" : "GreaterThan",
				"item_type" : "BOULDER",
				"reaction_id" : "ELECTRUM_MAKING",
				"value" : 0
			},
			{
				"bearing" : "GOLD",
				"condition" : "GreaterThan",
				"item_type" : "BOULDER",
				"reaction_id" : "ELECTRUM_MAKING",
				"value" : 0
			},
			{
				"condition" : "GreaterThan",
				"item_type" : "BAR",
				"material" : "COAL",
				"value" : 0
			}
		],
		"job" : "CustomReaction",
		"reaction" : "ELECTRUM_MAKING"
	},
	{
		"amount_left" : 0,
		"amount_total" : 0,
		"frequency" : "Daily",
		"id" : 459,
		"is_active" : false,
		"is_validated" : true,
		"item_conditions" : 
		[
			{
				"bearing" : "TIN",
				"condition" : "GreaterThan",
				"item_type" : "BOULDER",
				"reaction_id" : "PEWTER_FINE_MAKING",
				"value" : 0
			},
			{
				"bearing" : "COPPER",
				"condition" : "GreaterThan",
				"item_type" : "BOULDER",
				"reaction_id" : "PEWTER_FINE_MAKING",
				"value" : 0
			},
			{
				"condition" : "GreaterThan",
				"item_type" : "BAR",
				"material" : "COAL",
				"value" : 0
			}
		],
		"job" : "CustomReaction",
		"reaction" : "PEWTER_FINE_MAKING"
	},
	{
		"amount_left" : 0,
		"amount_total" : 0,
		"frequency" : "Daily",
		"id" : 460,
		"is_active" : false,
		"is_validated" : true,
		"item_conditions" : 
		[
			{
				"condition" : "GreaterThan",
				"item_type" : "BAR",
				"material" : "INORGANIC:NICKEL",
				"reaction_id" : "NICKEL_SILVER_MAKING",
				"value" : 0
			},
			{
				"condition" : "GreaterThan",
				"item_type" : "BAR",
				"material" : "INORGANIC:COPPER",
				"reaction_id" : "NICKEL_SILVER_MAKING",
				"value" : 0
			},
			{
				"condition" : "GreaterThan",
				"item_type" : "BAR",
				"material" : "INORGANIC:ZINC",
				"reaction_id" : "NICKEL_SILVER_MAKING",
				"value" : 0
			},
			{
				"condition" : "GreaterThan",
				"item_type" : "BAR",
				"material" : "COAL",
				"value" : 0
			}
		],
		"job" : "CustomReaction",
		"reaction" : "NICKEL_SILVER_MAKING"
	},
	{
		"amount_left" : 0,
		"amount_total" : 0,
		"frequency" : "Daily",
		"id" : 461,
		"is_active" : false,
		"is_validated" : true,
		"item_conditions" : 
		[
			{
				"condition" : "GreaterThan",
				"item_type" : "BAR",
				"material" : "INORGANIC:IRON",
				"reaction_id" : "PIG_IRON_MAKING",
				"value" : 0
			},
			{
				"condition" : "GreaterThan",
				"item_type" : "BOULDER",
				"reaction_class" : "FLUX",
				"reaction_id" : "PIG_IRON_MAKING",
				"value" : 0
			},
			{
				"condition" : "GreaterThan",
				"item_type" : "BAR",
				"material" : "COAL",
				"reaction_id" : "PIG_IRON_MAKING",
				"value" : 0
			}
		],
		"job" : "CustomReaction",
		"reaction" : "PIG_IRON_MAKING"
	},
	{
		"amount_left" : 0,
		"amount_total" : 0,
		"frequency" : "Daily",
		"id" : 462,
		"is_active" : false,
		"is_validated" : true,
		"item_conditions" : 
		[
			{
				"condition" : "GreaterThan",
				"item_type" : "BAR",
				"material" : "INORGANIC:GOLD",
				"reaction_id" : "ROSE_GOLD_MAKING",
				"value" : 0
			},
			{
				"condition" : "GreaterThan",
				"item_type" : "BAR",
				"material" : "INORGANIC:COPPER",
				"reaction_id" : "ROSE_GOLD_MAKING",
				"value" : 0
			},
			{
				"condition" : "GreaterThan",
				"item_type" : "BAR",
				"material" : "COAL",
				"value" : 0
			}
		],
		"job" : "CustomReaction",
		"reaction" : "ROSE_GOLD_MAKING"
	},
	{
		"amount_left" : 0,
		"amount_total" : 0,
		"frequency" : "Daily",
		"id" : 464,
		"is_active" : false,
		"is_validated" : true,
		"item_conditions" : 
		[
			{
				"condition" : "GreaterThan",
				"item_type" : "BAR",
				"material" : "INORGANIC:IRON",
				"reaction_id" : "STEEL_MAKING",
				"value" : 0
			},
			{
				"condition" : "GreaterThan",
				"item_type" : "BAR",
				"material" : "INORGANIC:PIG_IRON",
				"reaction_id" : "STEEL_MAKING",
				"value" : 0
			},
			{
				"condition" : "GreaterThan",
				"item_type" : "BOULDER",
				"reaction_class" : "FLUX",
				"reaction_id" : "STEEL_MAKING",
				"value" : 0
			},
			{
				"condition" : "GreaterThan",
				"item_type" : "BAR",
				"material" : "COAL",
				"reaction_id" : "STEEL_MAKING",
				"value" : 0
			},
			{
				"condition" : "GreaterThan",
				"item_type" : "BAR",
				"material" : "COAL",
				"value" : 0
			}
		],
		"job" : "CustomReaction",
		"reaction" : "STEEL_MAKING"
	},
	{
		"amount_left" : 0,
		"amount_total" : 0,
		"frequency" : "Daily",
		"id" : 465,
		"is_active" : false,
		"is_validated" : true,
		"item_conditions" : 
		[
			{
				"condition" : "GreaterThan",
				"item_type" : "BAR",
				"material" : "INORGANIC:SILVER",
				"reaction_id" : "STERLING_SILVER_MAKING",
				"value" : 0
			},
			{
				"condition" : "GreaterThan",
				"item_type" : "BAR",
				"material" : "INORGANIC:COPPER",
				"reaction_id" : "STERLING_SILVER_MAKING",
				"value" : 0
			},
			{
				"condition" : "GreaterThan",
				"item_type" : "BAR",
				"material" : "COAL",
				"value" : 0
			}
		],
		"job" : "CustomReaction",
		"reaction" : "STERLING_SILVER_MAKING"
	},
	{
		"amount_left" : 0,
		"amount_total" : 0,
		"frequency" : "Daily",
		"id" : 466,
		"is_active" : false,
		"is_validated" : true,
		"item_conditions" : 
		[
			{
				"bearing" : "TIN",
				"condition" : "GreaterThan",
				"item_type" : "BOULDER",
				"reaction_id" : "PEWTER_TRIFLE_MAKING",
				"value" : 0
			},
			{
				"bearing" : "COPPER",
				"condition" : "GreaterThan",
				"item_type" : "BOULDER",
				"reaction_id" : "PEWTER_TRIFLE_MAKING",
				"value" : 0
			},
			{
				"condition" : "GreaterThan",
				"item_type" : "BAR",
				"material" : "COAL",
				"value" : 0
			}
		],
		"job" : "CustomReaction",
		"reaction" : "PEWTER_TRIFLE_MAKING"
	},
	{
		"amount_left" : 0,
		"amount_total" : 0,
		"frequency" : "Daily",
		"id" : 468,
		"is_active" : false,
		"is_validated" : true,
		"item_conditions" : 
		[
			{
				"condition" : "GreaterThan",
				"item_type" : "BOULDER",
				"material" : "INORGANIC:BISMUTHINITE",
				"value" : 0
			},
			{
				"condition" : "GreaterThan",
				"item_type" : "BAR",
				"material" : "COAL",
				"value" : 0
			}
		],
		"job" : "SmeltOre",
		"material" : "INORGANIC:BISMUTHINITE"
	},
	{
		"amount_left" : 0,
		"amount_total" : 0,
		"frequency" : "Daily",
		"id" : 469,
		"is_active" : false,
		"is_validated" : true,
		"item_conditions" : 
		[
			{
				"condition" : "GreaterThan",
				"item_type" : "BOULDER",
				"material" : "INORGANIC:CASSITERITE",
				"value" : 0
			},
			{
				"condition" : "GreaterThan",
				"item_type" : "BAR",
				"material" : "COAL",
				"value" : 0
			}
		],
		"job" : "SmeltOre",
		"material" : "INORGANIC:CASSITERITE"
	},
	{
		"amount_left" : 0,
		"amount_total" : 0,
		"frequency" : "Daily",
		"id" : 471,
		"is_active" : false,
		"is_validated" : true,
		"item_conditions" : 
		[
			{
				"condition" : "GreaterThan",
				"item_type" : "BOULDER",
				"material" : "INORGANIC:GALENA",
				"value" : 0
			},
			{
				"condition" : "GreaterThan",
				"item_type" : "BAR",
				"material" : "COAL",
				"value" : 0
			}
		],
		"job" : "SmeltOre",
		"material" : "INORGANIC:GALENA"
	},
	{
		"amount_left" : 0,
		"amount_total" : 0,
		"frequency" : "Daily",
		"id" : 472,
		"is_active" : false,
		"is_validated" : true,
		"item_conditions" : 
		[
			{
				"condition" : "GreaterThan",
				"item_type" : "BOULDER",
				"material" : "INORGANIC:GARNIERITE",
				"value" : 0
			},
			{
				"condition" : "GreaterThan",
				"item_type" : "BAR",
				"material" : "COAL",
				"value" : 0
			}
		],
		"job" : "SmeltOre",
		"material" : "INORGANIC:GARNIERITE"
	},
	{
		"amount_left" : 0,
		"amount_total" : 0,
		"frequency" : "Daily",
		"id" : 473,
		"is_active" : false,
		"is_validated" : true,
		"item_conditions" : 
		[
			{
				"condition" : "GreaterThan",
				"item_type" : "BOULDER",
				"material" : "INORGANIC:HEMATITE",
				"value" : 0
			},
			{
				"condition" : "GreaterThan",
				"item_type" : "BAR",
				"material" : "COAL",
				"value" : 0
			}
		],
		"job" : "SmeltOre",
		"material" : "INORGANIC:HEMATITE"
	},
	{
		"amount_left" : 0,
		"amount_total" : 0,
		"frequency" : "Daily",
		"id" : 474,
		"is_active" : false,
		"is_validated" : true,
		"item_conditions" : 
		[
			{
				"condition" : "GreaterThan",
				"item_type" : "BOULDER",
				"material" : "INORGANIC:HORN_SILVER",
				"value" : 0
			},
			{
				"condition" : "GreaterThan",
				"item_type" : "BAR",
				"material" : "COAL",
				"value" : 0
			}
		],
		"job" : "SmeltOre",
		"material" : "INORGANIC:HORN_SILVER"
	},
	{
		"amount_left" : 0,
		"amount_total" : 0,
		"frequency" : "Daily",
		"id" : 476,
		"is_active" : false,
		"is_validated" : true,
		"item_conditions" : 
		[
			{
				"condition" : "GreaterThan",
				"item_type" : "BOULDER",
				"material" : "INORGANIC:LIMONITE",
				"value" : 0
			},
			{
				"condition" : "GreaterThan",
				"item_type" : "BAR",
				"material" : "COAL",
				"value" : 0
			}
		],
		"job" : "SmeltOre",
		"material" : "INORGANIC:LIMONITE"
	},
	{
		"amount_left" : 0,
		"amount_total" : 0,
		"frequency" : "Daily",
		"id" : 478,
		"is_active" : false,
		"is_validated" : true,
		"item_conditions" : 
		[
			{
				"condition" : "GreaterThan",
				"item_type" : "BOULDER",
				"material" : "INORGANIC:MAGNETITE",
				"value" : 0
			},
			{
				"condition" : "GreaterThan",
				"item_type" : "BAR",
				"material" : "COAL",
				"value" : 0
			}
		],
		"job" : "SmeltOre",
		"material" : "INORGANIC:MAGNETITE"
	},
	{
		"amount_left" : 0,
		"amount_total" : 0,
		"frequency" : "Daily",
		"id" : 479,
		"is_active" : false,
		"is_validated" : true,
		"item_conditions" : 
		[
			{
				"condition" : "GreaterThan",
				"item_type" : "BOULDER",
				"material" : "INORGANIC:MALACHITE",
				"value" : 0
			},
			{
				"condition" : "GreaterThan",
				"item_type" : "BAR",
				"material" : "COAL",
				"value" : 0
			}
		],
		"job" : "SmeltOre",
		"material" : "INORGANIC:MALACHITE"
	},
	{
		"amount_left" : 0,
		"amount_total" : 0,
		"frequency" : "Daily",
		"id" : 480,
		"is_active" : false,
		"is_validated" : true,
		"item_conditions" : 
		[
			{
				"condition" : "GreaterThan",
				"item_type" : "BOULDER",
				"material" : "INORGANIC:NATIVE_ALUMINUM",
				"value" : 0
			},
			{
				"condition" : "GreaterThan",
				"item_type" : "BAR",
				"material" : "COAL",
				"value" : 0
			}
		],
		"job" : "SmeltOre",
		"material" : "INORGANIC:NATIVE_ALUMINUM"
	},
	{
		"amount_left" : 0,
		"amount_total" : 0,
		"frequency" : "Daily",
		"id" : 481,
		"is_active" : false,
		"is_validated" : true,
		"item_conditions" : 
		[
			{
				"condition" : "GreaterThan",
				"item_type" : "BOULDER",
				"material" : "INORGANIC:NATIVE_COPPER",
				"value" : 0
			},
			{
				"condition" : "GreaterThan",
				"item_type" : "BAR",
				"material" : "COAL",
				"value" : 0
			}
		],
		"job" : "SmeltOre",
		"material" : "INORGANIC:NATIVE_COPPER"
	},
	{
		"amount_left" : 0,
		"amount_total" : 0,
		"frequency" : "Daily",
		"id" : 482,
		"is_active" : false,
		"is_validated" : true,
		"item_conditions" : 
		[
			{
				"condition" : "GreaterThan",
				"item_type" : "BOULDER",
				"material" : "INORGANIC:NATIVE_GOLD",
				"value" : 0
			},
			{
				"condition" : "GreaterThan",
				"item_type" : "BAR",
				"material" : "COAL",
				"value" : 0
			}
		],
		"job" : "SmeltOre",
		"material" : "INORGANIC:NATIVE_GOLD"
	},
	{
		"amount_left" : 0,
		"amount_total" : 0,
		"frequency" : "Daily",
		"id" : 484,
		"is_active" : false,
		"is_validated" : true,
		"item_conditions" : 
		[
			{
				"condition" : "GreaterThan",
				"item_type" : "BOULDER",
				"material" : "INORGANIC:NATIVE_PLATINUM",
				"value" : 0
			},
			{
				"condition" : "GreaterThan",
				"item_type" : "BAR",
				"material" : "COAL",
				"value" : 0
			}
		],
		"job" : "SmeltOre",
		"material" : "INORGANIC:NATIVE_PLATINUM"
	},
	{
		"amount_left" : 0,
		"amount_total" : 0,
		"frequency" : "Daily",
		"id" : 485,
		"is_active" : false,
		"is_validated" : true,
		"item_conditions" : 
		[
			{
				"condition" : "GreaterThan",
				"item_type" : "BOULDER",
				"material" : "INORGANIC:NATIVE_SILVER",
				"value" : 0
			},
			{
				"condition" : "GreaterThan",
				"item_type" : "BAR",
				"material" : "COAL",
				"value" : 0
			}
		],
		"job" : "SmeltOre",
		"material" : "INORGANIC:NATIVE_SILVER"
	},
	{
		"amount_left" : 0,
		"amount_total" : 0,
		"frequency" : "Daily",
		"id" : 486,
		"is_active" : false,
		"is_validated" : true,
		"item_conditions" : 
		[
			{
				"condition" : "GreaterThan",
				"item_type" : "BOULDER",
				"material" : "INORGANIC:SPHALERITE",
				"value" : 0
			},
			{
				"condition" : "GreaterThan",
				"item_type" : "BAR",
				"material" : "COAL",
				"value" : 0
			}
		],
		"job" : "SmeltOre",
		"material" : "INORGANIC:SPHALERITE"
	},
	{
		"amount_left" : 0,
		"amount_total" : 0,
		"frequency" : "Daily",
		"id" : 487,
		"is_active" : false,
		"is_validated" : true,
		"item_conditions" : 
		[
			{
				"condition" : "GreaterThan",
				"item_type" : "BOULDER",
				"material" : "INORGANIC:TETRAHEDRITE",
				"value" : 0
			},
			{
				"condition" : "GreaterThan",
				"item_type" : "BAR",
				"material" : "COAL",
				"value" : 0
			}
		],
		"job" : "SmeltOre",
		"material" : "INORGANIC:TETRAHEDRITE"
	}
]
